[
    {
      "Name": "Abayon, Judd Hernan C.",
      "Code": "jabayon",
      "Quote": "The only person you are destined to become is the person you decide to be.",
      "Email": "raphaelbihag00@gmail.com"
    },
    {
      "Name": "Andag, Ian Rafael S.",
      "Code": "iandag",
      "Quote": "Doubt is a pain too lonely to know that faith is its twin.",
      "Email": "raphaelbihag00@gmail.com"
    },
    {
      "Name": "Aseniero, Prince Judah M.",
      "Code": "paseniero",
      "Quote": "Innovation distinguishes between a leader and a follower.",
      "Email": "raphaelbihag00@gmail.com"
    },
    {
      "Name": "Beduya, CJ Menard B.",
      "Code": "cbeduya",
      "Quote": "The journey of a thousand miles begins with a single step.",
      "Email": "raphaelbihag00@gmail.com"
    },
    {
      "Name": "Cadampog, Rhojoane Rhaje M.",
      "Code": "rcadampog",
      "Quote": "Curiosity is the fuel of learning.",
      "Email": "raphaelbihag00@gmail.com"
    },
    {
      "Name": "Concepcion, Cris Oliver D.Z.",
      "Code": "cconcepcion",
      "Quote": "The best and most beautiful things in the world cannot be seen or even touched - they must be felt with the heart.",
      "Email": "raphaelbihag00@gmail.com"
    },
    {
      "Name": "De Guzman, Carl Adrian O.",
      "Code": "cdeguzman",
      "Quote": "It is during our darkest moments that we must focus to see the light.",
      "Email": "raphaelbihag00@gmail.com"
    },
    {
      "Name": "Garcia, Alek Emmanuel C.",
      "Code": "agarcia",
      "Quote": "Don't be afraid to give up the good to go for the great.",
      "Email": "raphaelbihag00@gmail.com"
    },
    {
      "Name": "Hofileña, Hans Neoncris T.",
      "Code": "hhofileña",
      "Quote": "Twenty years from now you will be more disappointed by the things that you didn’t do than by the ones you did do.",
      "Email": "raphaelbihag00@gmail.com"
    },
    {
      "Name": "Ilustrado, Arvy Novem Pol A.",
      "Code": "ailustrado",
      "Quote": "The mind is everything. What you think you become.",
      "Email": "raphaelbihag00@gmail.com"
    },
    {
      "Name": "Jerusalem, Yno Jessius R.",
      "Code": "yjerusalem",
      "Quote": "The only way to do great work is to love what you do.",
      "Email": "raphaelbihag00@gmail.com"
    },
    {
      "Name": "Jumuad, Jessam Nikolai C.",
      "Code": "jjumuad",
      "Quote": "You don't have to be great to start, but you have to start to be great.",
      "Email": "raphaelbihag00@gmail.com"
    },
    {
      "Name": "Molanda, Jorel Jared Jay C.",
      "Code": "jmolanda",
      "Quote": "Life is 10% what happens to you and 90% how you react to it.",
      "Email": "raphaelbihag00@gmail.com"
    },
    {
      "Name": "Olvis, BJ Nathaniel Hope B.",
      "Code": "bolvis",
      "Quote": "The difference between ordinary and extraordinary is that little extra.",
      "Email": "raphaelbihag00@gmail.com"
    },
    {
      "Name": "Parame, Prince Vincent A.",
      "Code": "pparame",
      "Quote": "The best time to plant a tree was 20 years ago. The second best time is now.",
      "Email": "raphaelbihag00@gmail.com"
    },
    {
      "Name": "Solima, Jan Gregory E.",
      "Code": "jsolima",
      "Quote": "A dream doesn't become reality through magic; it takes sweat, determination, and hard work.",
      "Email": "raphaelbihag00@gmail.com"
    },
    {
      "Name": "Tabaculde, Atlantis Gal M.",
      "Code": "atabaculde",
      "Quote": "The only limit to our realization of tomorrow will be our doubts of today.",
      "Email": "raphaelbihag00@gmail.com"
    },
    {
      "Name": "Aoanan, Sophia Danielle Marithe O.",
      "Code": "saoanan",
      "Quote": "The best revenge is massive success.",
      "Email": "raphaelbihag00@gmail.com"
    },
    {
      "Name": "Baje, Nicole Ashley G.",
      "Code": "nbaje",
      "Quote": "If you can't fly then run, if you can't run then walk, if you can't walk then crawl, but whatever you do you have to keep moving forward.",
      "Email": "raphaelbihag00@gmail.com"
    },
    {
      "Name": "Caño, Andrea Viktoria M.",
      "Code": "acaño",
      "Quote": "The only person you are destined to become is the person you decide to be.",
      "Email": "raphaelbihag00@gmail.com"
    },
    {
      "Name": "Chiong, Patricia Ann L.",
      "Code": "pchiong",
      "Quote": "The purpose of life is not to be happy. It is to be useful, to be honorable, to be compassionate, to have it make some difference that you have lived and lived well.",
      "Email": "raphaelbihag00@gmail.com"
    },
    {
      "Name": "Dael, Ann Marielle U.",
      "Code": "adael",
      "Quote": "You may say I'm a dreamer, but I'm not the only one. I hope someday you'll join us. And the world will live as one.",
      "Email": "raphaelbihag00@gmail.com"
    },
    {
      "Name": "Dionaldo, Kyla B.",
      "Code": "kdionaldo",
      "Quote": "The future belongs to those who believe in the beauty of their dreams.",
      "Email": "raphaelbihag00@gmail.com"
    },
    {
      "Name": "Gelito, Glenda D.",
      "Code": "ggelito",
      "Quote": "If you can't fly then run, if you can't run then walk, if you can't walk then crawl, but whatever you do you have to keep moving forward.",
      "Email": "raphaelbihag00@gmail.com"
    },
    {
      "Name": "Lumingkit, Noelly B.",
      "Code": "nlumingkit",
      "Quote": "The only person you are destined to become is the person you decide to be.",
      "Email": "raphaelbihag00@gmail.com"
    },
    {
      "Name": "Montipon, Ella Mae",
      "Code": "emontipon",
      "Quote": "The purpose of life is not to be happy. It is to be useful, to be honorable, to be compassionate, to have it make some difference that you have lived and lived well.",
      "Email": "raphaelbihag00@gmail.com"
    },
    {
      "Name": "Rosel, Andrea Margarette B.",
      "Code": "arosel",
      "Quote": "You may say I'm a dreamer, but I'm not the only one. I hope someday you'll join us. And the world will live as one.",
      "Email": "raphaelbihag00@gmail.com"
    },
    {
      "Name": "Son, Aeshelle Carmelle F.",
      "Code": "ason",
      "Quote": "The future belongs to those who believe in the beauty of their dreams.",
      "Email": "raphaelbihag00@gmail.com"
    },
    {
      "Name": "Tigoy, Shyana Aisylle R.",
      "Code": "stigoy",
      "Quote": "If you can't fly then run, if you can't run then walk, if you can't walk then crawl, but whatever you do you have to keep moving forward.",
      "Email": "raphaelbihag00@gmail.com"
    },
    {
      "Name": "Timbreza, Chen J.",
      "Code": "ctimbreza",
      "Quote": "The only person you are destined to become is the person you decide to be.",
      "Email": "raphaelbihag00@gmail.com"
    }
]